vaiz/__init__.py
vaiz/client.py
vaiz/py.typed
vaiz/api/__init__.py
vaiz/api/base.py
vaiz/api/boards.py
vaiz/api/comments.py
vaiz/api/documents.py
vaiz/api/members.py
vaiz/api/milestones.py
vaiz/api/profile.py
vaiz/api/projects.py
vaiz/api/spaces.py
vaiz/api/tasks.py
vaiz/api/upload.py
vaiz/helpers/__init__.py
vaiz/helpers/custom_fields.py
vaiz/helpers/document_structure.py
vaiz/models/__init__.py
vaiz/models/base.py
vaiz/models/boards.py
vaiz/models/comments.py
vaiz/models/documents.py
vaiz/models/enums.py
vaiz/models/members.py
vaiz/models/milestones.py
vaiz/models/profile.py
vaiz/models/projects.py
vaiz/models/spaces.py
vaiz/models/tasks.py
vaiz/models/upload.py
vaiz_sdk-0.17.0.dist-info/licenses/LICENSE
vaiz_sdk-0.17.0.dist-info/METADATA
vaiz_sdk-0.17.0.dist-info/WHEEL
vaiz_sdk-0.17.0.dist-info/top_level.txt
vaiz_sdk-0.17.0.dist-info/RECORD
