Metadata-Version: 2.4
Name: vaiz-sdk
Version: 0.17.0
Summary: Official SDK for interacting with the Vaiz API
Author-email: Vaiz <mail@vaiz.com>
License-Expression: MIT
Project-URL: Homepage, https://github.com/vaizcom/vaiz-python-sdk
Project-URL: Repository, https://github.com/vaizcom/vaiz-python-sdk
Project-URL: Issues, https://github.com/vaizcom/vaiz-python-sdk/issues
Classifier: Development Status :: 4 - Beta
Classifier: Intended Audience :: Developers
Classifier: Topic :: Software Development :: Libraries
Classifier: Programming Language :: Python :: 3
Classifier: Programming Language :: Python :: 3.8
Classifier: Programming Language :: Python :: 3.9
Classifier: Programming Language :: Python :: 3.10
Classifier: Programming Language :: Python :: 3.11
Classifier: Programming Language :: Python :: 3.12
Classifier: Typing :: Typed
Requires-Python: >=3.8
License-File: LICENSE
Requires-Dist: requests>=2.31.0
Requires-Dist: pydantic>=2.0
Requires-Dist: python-dotenv>=0.9.0
Provides-Extra: dev
Requires-Dist: pytest>=8.0.0; extra == "dev"
Requires-Dist: pytest-mock>=3.12.0; extra == "dev"
Dynamic: license-file
